facts_gene/__init__.py
facts_gene/facts_gen_commons.py
facts_gene/facts_gen_from_fg.py
facts_gene/facts_gen_tables_ntct.py
facts_gene/facts_gen_var_ntct.py
facts_gene/facts_gene_cisco.py
facts_gene/facts_gene_com.py
facts_gene/facts_gene_juniper.py
facts_gene/general.py
facts_gene/inside_fsm/1.txt
facts_gene/inside_fsm/2.txt
facts_gene-0.0.6.dist-info/LICENSE
facts_gene-0.0.6.dist-info/METADATA
facts_gene-0.0.6.dist-info/WHEEL
facts_gene-0.0.6.dist-info/top_level.txt
facts_gene-0.0.6.dist-info/RECORD
