Metadata-Version: 2.1
Name: facts-gene
Version: 0.0.6
Summary: facts_gene for Networking Geeks
Home-page: https://github.com/alias1978/facts_gene
Author: ALIASGAR - ALI
Author-email: aholo2000@gmail.com
Classifier: Programming Language :: Python :: 3
Classifier: License :: OSI Approved :: MIT License
Classifier: Operating System :: OS Independent
Requires-Python: >=3.7
License-File: LICENSE
Requires-Dist: pandas
Requires-Dist: numpy
Requires-Dist: xlrd
Requires-Dist: openpyxl
Requires-Dist: nettoolkit
Requires-Dist: capture-it
